qhbmlib/__init__.py
qhbmlib/data/__init__.py
qhbmlib/data/qhbm_data.py
qhbmlib/data/quantum_data.py
qhbmlib/inference/__init__.py
qhbmlib/inference/ebm.py
qhbmlib/inference/ebm_utils.py
qhbmlib/inference/qhbm.py
qhbmlib/inference/qhbm_utils.py
qhbmlib/inference/qmhl_loss.py
qhbmlib/inference/qnn.py
qhbmlib/inference/qnn_utils.py
qhbmlib/inference/vqt_loss.py
qhbmlib/models/__init__.py
qhbmlib/models/circuit.py
qhbmlib/models/circuit_utils.py
qhbmlib/models/energy.py
qhbmlib/models/energy_utils.py
qhbmlib/models/hamiltonian.py
qhbmlib/utils.py
qhbmlib-0.3.0.dist-info/LICENSE
qhbmlib-0.3.0.dist-info/WHEEL
qhbmlib-0.3.0.dist-info/METADATA
qhbmlib-0.3.0.dist-info/RECORD
