Metadata-Version: 2.1
Name: qhbmlib
Version: 0.3.0
Summary: Quantum Hamiltonian-Based Models built on TensorFlow Quantum
Home-page: https://github.com/google/qhbm-library
License: Apache-2.0
Keywords: quantum-computing
Author: The QHBM Library Authors
Author-email: no-reply@google.com
Requires-Python: >=3.7,<3.10
Classifier: Development Status :: 3 - Alpha
Classifier: Intended Audience :: Science/Research
Classifier: License :: OSI Approved :: Apache Software License
Classifier: Programming Language :: Python :: 3
Classifier: Programming Language :: Python :: 3.7
Classifier: Programming Language :: Python :: 3.8
Classifier: Programming Language :: Python :: 3.9
Classifier: Topic :: Scientific/Engineering
Classifier: Topic :: Scientific/Engineering :: Artificial Intelligence
Classifier: Topic :: Scientific/Engineering :: Mathematics
Classifier: Topic :: Scientific/Engineering :: Physics
Requires-Dist: tensorflow (==2.7.0)
Requires-Dist: tensorflow-probability (==0.15.0)
Requires-Dist: tensorflow-quantum (==0.6.1)
Project-URL: Repository, https://github.com/google/qhbm-library
